funlib/show/neuroglancer/__init__.py
funlib/show/neuroglancer/add_layer.py
funlib/show/neuroglancer/cli.py
funlib/show/neuroglancer/scale_pyramid.py
funlib/show/neuroglancer/video_tool.py
funlib.show.neuroglancer-0.2.dist-info/METADATA
funlib.show.neuroglancer-0.2.dist-info/WHEEL
funlib.show.neuroglancer-0.2.dist-info/entry_points.txt
funlib.show.neuroglancer-0.2.dist-info/top_level.txt
funlib.show.neuroglancer-0.2.dist-info/RECORD
